{
  "id": 10308,
  "name": "Staraptor-mega",
  "species": "Pokémon",
  "type": [
    "Fighting",
    "Flying"
  ],
  "typeDetails": [
    {
      "name": "Fighting",
      "slot": 1
    },
    {
      "name": "Flying",
      "slot": 2
    }
  ],
  "height": 1.9,
  "weight": 50.0,
  "abilities": [],
  "baseStats": {
    "hp": 85,
    "attack": 140,
    "defense": 100,
    "specialAttack": 60,
    "specialDefense": 90,
    "speed": 110
  },
  "description": "",
  "flavorTexts": [],
  "colorPalette": {
    "primary": "#C03028",
    "secondary": "#A8A878",
    "accent": "#F8D030",
    "background": "#F8F8F8",
    "text": "#2C2C2C",
    "highlights": [
      "#C03028",
      "#A8A878",
      "#F8D030"
    ]
  },
  "artwork": {
    "official": "/pokemon/10308.png",
    "front": null,
    "back": null,
    "shiny": null,
    "back_shiny": null,
    "front_female": null,
    "back_female": null,
    "front_shiny_female": null,
    "back_shiny_female": null
  },
  "evolution": {
    "stage": 1,
    "generation": 1
  },
  "moves": [],
  "habitat": "Unknown",
  "generation": 1,
  "rarity": "Common",
  "baseExperience": null,
  "order": -1,
  "isDefault": false,
  "captureRate": 45,
  "baseHappiness": 70,
  "growthRate": "medium",
  "hatchCounter": 20,
  "hasGenderDifferences": false,
  "genderRate": -1,
  "forms": [],
  "varieties": [],
  "heldItems": [],
  "cries": {
    "latest": null,
    "legacy": null
  }
}