{
  "id": 128,
  "name": "Tauros",
  "species": "Wild Bull Pokémon",
  "type": [
    "Normal"
  ],
  "typeDetails": [
    {
      "name": "Normal",
      "slot": 1
    }
  ],
  "height": 1.4,
  "weight": 88.4,
  "abilities": [
    {
      "name": "Intimidate",
      "url": "https://pokeapi.co/api/v2/ability/22/",
      "is_hidden": false,
      "slot": 1
    },
    {
      "name": "Anger point",
      "url": "https://pokeapi.co/api/v2/ability/83/",
      "is_hidden": false,
      "slot": 2
    },
    {
      "name": "Sheer force",
      "url": "https://pokeapi.co/api/v2/ability/125/",
      "is_hidden": true,
      "slot": 3
    }
  ],
  "baseStats": {
    "hp": 75,
    "attack": 100,
    "defense": 95,
    "specialAttack": 40,
    "specialDefense": 70,
    "speed": 110
  },
  "description": "When it targets an enemy, it charges furiously while whipping its body with its long tails.",
  "flavorTexts": [
    {
      "text": "When it targets an enemy, it charges furiously while whipping its body with its long tails.",
      "version": "red"
    },
    {
      "text": "When it targets an enemy, it charges furiously while whipping its body with its long tails.",
      "version": "blue"
    },
    {
      "text": "A rowdy POKéMON with a lot of stamina. Once running, it won't stop until it hits something.",
      "version": "yellow"
    },
    {
      "text": "They fight each other by locking horns. The herd's protector takes pride in its bat­ tle-scarred horns.",
      "version": "gold"
    },
    {
      "text": "After heightening its will to fight by whipping itself with its three tails, it charges at full speed.",
      "version": "silver"
    }
  ],
  "colorPalette": {
    "primary": "#dea44a",
    "secondary": "#b48331",
    "accent": "#624a31",
    "background": "#F8F8F8",
    "text": "#2C2C2C",
    "highlights": [
      "#dea44a",
      "#b48331",
      "#624a31"
    ]
  },
  "artwork": {
    "official": "https://raw.githubusercontent.com/PokeAPI/sprites/master/sprites/pokemon/other/official-artwork/128.png",
    "front": "https://raw.githubusercontent.com/PokeAPI/sprites/master/sprites/pokemon/128.png",
    "back": "https://raw.githubusercontent.com/PokeAPI/sprites/master/sprites/pokemon/back/128.png",
    "shiny": "https://raw.githubusercontent.com/PokeAPI/sprites/master/sprites/pokemon/shiny/128.png",
    "back_shiny": "https://raw.githubusercontent.com/PokeAPI/sprites/master/sprites/pokemon/back/shiny/128.png",
    "front_female": null,
    "back_female": null,
    "front_shiny_female": null,
    "back_shiny_female": null
  },
  "evolution": [
    {
      "name": "Tauros",
      "level": 1,
      "details": []
    }
  ],
  "moves": [
    {
      "name": "Stomp",
      "url": "https://pokeapi.co/api/v2/move/23/",
      "type": "Normal",
      "power": 65,
      "accuracy": 100,
      "pp": 20,
      "damage_class": "physical",
      "priority": 0
    },
    {
      "name": "Headbutt",
      "url": "https://pokeapi.co/api/v2/move/29/",
      "type": "Normal",
      "power": 70,
      "accuracy": 100,
      "pp": 15,
      "damage_class": "physical",
      "priority": 0
    },
    {
      "name": "Horn Attack",
      "url": "https://pokeapi.co/api/v2/move/30/",
      "type": "Normal",
      "power": 65,
      "accuracy": 100,
      "pp": 25,
      "damage_class": "physical",
      "priority": 0
    },
    {
      "name": "Horn Drill",
      "url": "https://pokeapi.co/api/v2/move/32/",
      "type": "Normal",
      "power": null,
      "accuracy": 30,
      "pp": 5,
      "damage_class": "physical",
      "priority": 0
    },
    {
      "name": "Tackle",
      "url": "https://pokeapi.co/api/v2/move/33/",
      "type": "Normal",
      "power": 40,
      "accuracy": 100,
      "pp": 35,
      "damage_class": "physical",
      "priority": 0
    },
    {
      "name": "Body Slam",
      "url": "https://pokeapi.co/api/v2/move/34/",
      "type": "Normal",
      "power": 85,
      "accuracy": 100,
      "pp": 15,
      "damage_class": "physical",
      "priority": 0
    },
    {
      "name": "Take Down",
      "url": "https://pokeapi.co/api/v2/move/36/",
      "type": "Normal",
      "power": 90,
      "accuracy": 85,
      "pp": 20,
      "damage_class": "physical",
      "priority": 0
    },
    {
      "name": "Thrash",
      "url": "https://pokeapi.co/api/v2/move/37/",
      "type": "Normal",
      "power": 120,
      "accuracy": 100,
      "pp": 10,
      "damage_class": "physical",
      "priority": 0
    },
    {
      "name": "Double Edge",
      "url": "https://pokeapi.co/api/v2/move/38/",
      "type": "Normal",
      "power": 120,
      "accuracy": 100,
      "pp": 15,
      "damage_class": "physical",
      "priority": 0
    },
    {
      "name": "Tail Whip",
      "url": "https://pokeapi.co/api/v2/move/39/",
      "type": "Normal",
      "power": null,
      "accuracy": 100,
      "pp": 30,
      "damage_class": "status",
      "priority": 0
    },
    {
      "name": "Leer",
      "url": "https://pokeapi.co/api/v2/move/43/",
      "type": "Normal",
      "power": null,
      "accuracy": 100,
      "pp": 30,
      "damage_class": "status",
      "priority": 0
    },
    {
      "name": "Flamethrower",
      "url": "https://pokeapi.co/api/v2/move/53/",
      "type": "Fire",
      "power": 90,
      "accuracy": 100,
      "pp": 15,
      "damage_class": "special",
      "priority": 0
    },
    {
      "name": "Surf",
      "url": "https://pokeapi.co/api/v2/move/57/",
      "type": "Water",
      "power": 90,
      "accuracy": 100,
      "pp": 15,
      "damage_class": "special",
      "priority": 0
    },
    {
      "name": "Ice Beam",
      "url": "https://pokeapi.co/api/v2/move/58/",
      "type": "Ice",
      "power": 90,
      "accuracy": 100,
      "pp": 10,
      "damage_class": "special",
      "priority": 0
    },
    {
      "name": "Blizzard",
      "url": "https://pokeapi.co/api/v2/move/59/",
      "type": "Ice",
      "power": 110,
      "accuracy": 70,
      "pp": 5,
      "damage_class": "special",
      "priority": 0
    }
  ],
  "habitat": "Grassland",
  "generation": 1,
  "rarity": "Common",
  "baseExperience": 172,
  "order": 209,
  "isDefault": true,
  "captureRate": 45,
  "baseHappiness": 70,
  "growthRate": "slow",
  "hatchCounter": 20,
  "hasGenderDifferences": false,
  "genderRate": 0,
  "forms": [
    {
      "name": "Tauros",
      "raw_name": "tauros",
      "form_name": "",
      "is_mega": false,
      "is_gigantamax": false,
      "is_battle_only": false,
      "is_default": true,
      "sprites": {
        "front_default": "https://raw.githubusercontent.com/PokeAPI/sprites/master/sprites/pokemon/128.png",
        "back_default": "https://raw.githubusercontent.com/PokeAPI/sprites/master/sprites/pokemon/back/128.png",
        "front_shiny": "https://raw.githubusercontent.com/PokeAPI/sprites/master/sprites/pokemon/shiny/128.png",
        "back_shiny": "https://raw.githubusercontent.com/PokeAPI/sprites/master/sprites/pokemon/back/shiny/128.png",
        "front_female": null,
        "back_female": null
      }
    }
  ],
  "varieties": [
    {
      "name": "Tauros",
      "raw_name": "tauros",
      "is_default": true,
      "url": "https://pokeapi.co/api/v2/pokemon/128/",
      "type": ""
    },
    {
      "name": "Tauros paldea combat breed",
      "raw_name": "tauros-paldea-combat-breed",
      "is_default": false,
      "url": "https://pokeapi.co/api/v2/pokemon/10250/",
      "type": "Paldean"
    },
    {
      "name": "Tauros paldea blaze breed",
      "raw_name": "tauros-paldea-blaze-breed",
      "is_default": false,
      "url": "https://pokeapi.co/api/v2/pokemon/10251/",
      "type": "Paldean"
    },
    {
      "name": "Tauros paldea aqua breed",
      "raw_name": "tauros-paldea-aqua-breed",
      "is_default": false,
      "url": "https://pokeapi.co/api/v2/pokemon/10252/",
      "type": "Paldean"
    }
  ],
  "heldItems": [],
  "cries": {
    "latest": "https://raw.githubusercontent.com/PokeAPI/cries/main/cries/pokemon/latest/128.ogg",
    "legacy": "https://raw.githubusercontent.com/PokeAPI/cries/main/cries/pokemon/legacy/128.ogg"
  },
  "names": {
    "ja-Hrkt": "ケンタロス",
    "roomaji": "Kentauros",
    "ko": "켄타로스",
    "zh-Hant": "肯泰羅",
    "fr": "Tauros",
    "de": "Tauros",
    "es": "Tauros",
    "it": "Tauros",
    "en": "Tauros",
    "ja": "ケンタロス",
    "zh-Hans": "肯泰罗"
  }
}