{
  "id": 518,
  "name": "Musharna",
  "species": "Drowsing Pokémon",
  "type": [
    "Psychic"
  ],
  "typeDetails": [
    {
      "name": "Psychic",
      "slot": 1
    }
  ],
  "height": 1.1,
  "weight": 60.5,
  "abilities": [
    {
      "name": "Forewarn",
      "url": "https://pokeapi.co/api/v2/ability/108/",
      "is_hidden": false,
      "slot": 1
    },
    {
      "name": "Synchronize",
      "url": "https://pokeapi.co/api/v2/ability/28/",
      "is_hidden": false,
      "slot": 2
    },
    {
      "name": "Telepathy",
      "url": "https://pokeapi.co/api/v2/ability/140/",
      "is_hidden": true,
      "slot": 3
    }
  ],
  "baseStats": {
    "hp": 116,
    "attack": 55,
    "defense": 85,
    "specialAttack": 107,
    "specialDefense": 95,
    "speed": 29
  },
  "description": "The mist emanating from their foreheads is packed with the dreams of people and Pokémon.",
  "flavorTexts": [
    {
      "text": "The mist emanating from their foreheads is packed with the dreams of people and Pokémon.",
      "version": "black"
    },
    {
      "text": "With the mist from its forehead, it can create shapes of things from dreams it has eaten.",
      "version": "white"
    },
    {
      "text": "The dream mist coming from its forehead changes into many different colors depending on the dream that was eaten.",
      "version": "black-2"
    },
    {
      "text": "The dream mist coming from its forehead changes into many different colors depending on the dream that was eaten.",
      "version": "white-2"
    },
    {
      "text": "The mist emanating from their foreheads is packed with the dreams of people and Pokémon.",
      "version": "x"
    }
  ],
  "colorPalette": {
    "primary": "#de7bbd",
    "secondary": "#947bde",
    "accent": "#ffc5cd",
    "background": "#F8F8F8",
    "text": "#2C2C2C",
    "highlights": [
      "#de7bbd",
      "#947bde",
      "#ffc5cd"
    ]
  },
  "artwork": {
    "official": "https://raw.githubusercontent.com/PokeAPI/sprites/master/sprites/pokemon/other/official-artwork/518.png",
    "front": "https://raw.githubusercontent.com/PokeAPI/sprites/master/sprites/pokemon/518.png",
    "back": "https://raw.githubusercontent.com/PokeAPI/sprites/master/sprites/pokemon/back/518.png",
    "shiny": "https://raw.githubusercontent.com/PokeAPI/sprites/master/sprites/pokemon/shiny/518.png",
    "back_shiny": "https://raw.githubusercontent.com/PokeAPI/sprites/master/sprites/pokemon/back/shiny/518.png",
    "front_female": null,
    "back_female": null,
    "front_shiny_female": null,
    "back_shiny_female": null
  },
  "evolution": [
    {
      "name": "Munna",
      "level": 1,
      "details": []
    },
    {
      "name": "Musharna",
      "level": 2,
      "details": [
        {
          "item": "moon stone",
          "trigger": "use item"
        }
      ]
    }
  ],
  "moves": [
    {
      "name": "Psybeam",
      "url": "https://pokeapi.co/api/v2/move/60/",
      "type": "Psychic",
      "power": 65,
      "accuracy": 100,
      "pp": 20,
      "damage_class": "special",
      "priority": 0
    },
    {
      "name": "Hyper Beam",
      "url": "https://pokeapi.co/api/v2/move/63/",
      "type": "Normal",
      "power": 150,
      "accuracy": 90,
      "pp": 5,
      "damage_class": "special",
      "priority": 0
    },
    {
      "name": "Thunder Wave",
      "url": "https://pokeapi.co/api/v2/move/86/",
      "type": "Electric",
      "power": null,
      "accuracy": 90,
      "pp": 20,
      "damage_class": "status",
      "priority": 0
    },
    {
      "name": "Toxic",
      "url": "https://pokeapi.co/api/v2/move/92/",
      "type": "Poison",
      "power": null,
      "accuracy": 90,
      "pp": 10,
      "damage_class": "status",
      "priority": 0
    },
    {
      "name": "Psychic",
      "url": "https://pokeapi.co/api/v2/move/94/",
      "type": "Psychic",
      "power": 90,
      "accuracy": 100,
      "pp": 10,
      "damage_class": "special",
      "priority": 0
    },
    {
      "name": "Hypnosis",
      "url": "https://pokeapi.co/api/v2/move/95/",
      "type": "Psychic",
      "power": null,
      "accuracy": 60,
      "pp": 20,
      "damage_class": "status",
      "priority": 0
    },
    {
      "name": "Double Team",
      "url": "https://pokeapi.co/api/v2/move/104/",
      "type": "Normal",
      "power": null,
      "accuracy": null,
      "pp": 15,
      "damage_class": "status",
      "priority": 0
    },
    {
      "name": "Defense Curl",
      "url": "https://pokeapi.co/api/v2/move/111/",
      "type": "Normal",
      "power": null,
      "accuracy": null,
      "pp": 40,
      "damage_class": "status",
      "priority": 0
    },
    {
      "name": "Light Screen",
      "url": "https://pokeapi.co/api/v2/move/113/",
      "type": "Psychic",
      "power": null,
      "accuracy": null,
      "pp": 30,
      "damage_class": "status",
      "priority": 0
    },
    {
      "name": "Reflect",
      "url": "https://pokeapi.co/api/v2/move/115/",
      "type": "Psychic",
      "power": null,
      "accuracy": null,
      "pp": 20,
      "damage_class": "status",
      "priority": 0
    },
    {
      "name": "Swift",
      "url": "https://pokeapi.co/api/v2/move/129/",
      "type": "Normal",
      "power": 60,
      "accuracy": null,
      "pp": 20,
      "damage_class": "special",
      "priority": 0
    },
    {
      "name": "Amnesia",
      "url": "https://pokeapi.co/api/v2/move/133/",
      "type": "Psychic",
      "power": null,
      "accuracy": null,
      "pp": 20,
      "damage_class": "status",
      "priority": 0
    },
    {
      "name": "Dream Eater",
      "url": "https://pokeapi.co/api/v2/move/138/",
      "type": "Psychic",
      "power": 100,
      "accuracy": 100,
      "pp": 15,
      "damage_class": "special",
      "priority": 0
    },
    {
      "name": "Flash",
      "url": "https://pokeapi.co/api/v2/move/148/",
      "type": "Normal",
      "power": null,
      "accuracy": 100,
      "pp": 20,
      "damage_class": "status",
      "priority": 0
    },
    {
      "name": "Rest",
      "url": "https://pokeapi.co/api/v2/move/156/",
      "type": "Psychic",
      "power": null,
      "accuracy": null,
      "pp": 5,
      "damage_class": "status",
      "priority": 0
    }
  ],
  "habitat": "Unknown",
  "generation": 1,
  "rarity": "Common",
  "baseExperience": 170,
  "order": 633,
  "isDefault": true,
  "captureRate": 75,
  "baseHappiness": 70,
  "growthRate": "fast",
  "hatchCounter": 10,
  "hasGenderDifferences": false,
  "genderRate": 4,
  "forms": [
    {
      "name": "Musharna",
      "raw_name": "musharna",
      "form_name": "",
      "is_mega": false,
      "is_gigantamax": false,
      "is_battle_only": false,
      "is_default": true,
      "sprites": {
        "front_default": "https://raw.githubusercontent.com/PokeAPI/sprites/master/sprites/pokemon/518.png",
        "back_default": "https://raw.githubusercontent.com/PokeAPI/sprites/master/sprites/pokemon/back/518.png",
        "front_shiny": "https://raw.githubusercontent.com/PokeAPI/sprites/master/sprites/pokemon/shiny/518.png",
        "back_shiny": "https://raw.githubusercontent.com/PokeAPI/sprites/master/sprites/pokemon/back/shiny/518.png",
        "front_female": null,
        "back_female": null
      }
    }
  ],
  "varieties": [
    {
      "name": "Musharna",
      "raw_name": "musharna",
      "is_default": true,
      "url": "https://pokeapi.co/api/v2/pokemon/518/",
      "type": ""
    }
  ],
  "heldItems": [],
  "cries": {
    "latest": "https://raw.githubusercontent.com/PokeAPI/cries/main/cries/pokemon/latest/518.ogg",
    "legacy": "https://raw.githubusercontent.com/PokeAPI/cries/main/cries/pokemon/legacy/518.ogg"
  },
  "names": {
    "ja-Hrkt": "ムシャーナ",
    "roomaji": "Musharna",
    "ko": "몽얌나",
    "zh-Hant": "夢夢蝕",
    "fr": "Mushana",
    "de": "Somnivora",
    "es": "Musharna",
    "it": "Musharna",
    "en": "Musharna",
    "ja": "ムシャーナ",
    "zh-Hans": "梦梦蚀"
  },
  "shinyColorPalette": {
    "highlights": [
      "#9c73cd",
      "#529cc5",
      "#ffb4c5"
    ],
    "primary": "#9c73cd",
    "secondary": "#529cc5",
    "accent": "#ffb4c5"
  }
}