{
  "id": 795,
  "name": "Pheromosa",
  "species": "Lissome Pok\u00e9mon",
  "type": [
    "Bug",
    "Fighting"
  ],
  "typeDetails": [
    {
      "name": "Bug",
      "slot": 1
    },
    {
      "name": "Fighting",
      "slot": 2
    }
  ],
  "height": 1.8,
  "weight": 25.0,
  "abilities": [
    {
      "name": "Beast boost",
      "url": "https://pokeapi.co/api/v2/ability/224/",
      "is_hidden": false,
      "slot": 1
    }
  ],
  "baseStats": {
    "hp": 71,
    "attack": 137,
    "defense": 37,
    "specialAttack": 137,
    "specialDefense": 37,
    "speed": 151
  },
  "description": "One of the dangerous Ultra Beasts, it has been spotted running across the land at terrific speeds.",
  "flavorTexts": [
    {
      "text": "One of the dangerous Ultra Beasts, it has been spotted running across the land at terrific speeds.",
      "version": "sun"
    },
    {
      "text": "One of the Ultra Beasts. It refuses to touch anything, perhaps because it senses some uncleanness in this world.",
      "version": "moon"
    },
    {
      "text": "A life-form that lives in another world, its body is thin and supple, but it also possesses great power.",
      "version": "ultra-sun"
    },
    {
      "text": "Although it\u2019s alien to this world and a danger here, it\u2019s apparently a common organism in the world where it normally lives.",
      "version": "ultra-moon"
    }
  ],
  "colorPalette": {
    "primary": "#A8B820",
    "secondary": "#78C850",
    "accent": "#F8D030",
    "background": "#F8F8F8",
    "text": "#2C2C2C",
    "highlights": [
      "#A8B820",
      "#78C850",
      "#F8D030"
    ]
  },
  "artwork": {
    "official": "https://raw.githubusercontent.com/PokeAPI/sprites/master/sprites/pokemon/other/official-artwork/795.png",
    "front": "https://raw.githubusercontent.com/PokeAPI/sprites/master/sprites/pokemon/795.png",
    "back": "https://raw.githubusercontent.com/PokeAPI/sprites/master/sprites/pokemon/back/795.png",
    "shiny": "https://raw.githubusercontent.com/PokeAPI/sprites/master/sprites/pokemon/shiny/795.png",
    "back_shiny": "https://raw.githubusercontent.com/PokeAPI/sprites/master/sprites/pokemon/back/shiny/795.png",
    "front_female": null,
    "back_female": null,
    "front_shiny_female": null,
    "back_shiny_female": null
  },
  "evolution": [
    {
      "name": "Pheromosa",
      "level": 1,
      "details": []
    }
  ],
  "moves": [
    {
      "name": "Stomp",
      "url": "https://pokeapi.co/api/v2/move/23/",
      "type": "Normal",
      "power": 65,
      "accuracy": 100,
      "pp": 20,
      "damage_class": "physical",
      "priority": 0
    },
    {
      "name": "Double Kick",
      "url": "https://pokeapi.co/api/v2/move/24/",
      "type": "Fighting",
      "power": 30,
      "accuracy": 100,
      "pp": 30,
      "damage_class": "physical",
      "priority": 0
    },
    {
      "name": "Jump Kick",
      "url": "https://pokeapi.co/api/v2/move/26/",
      "type": "Fighting",
      "power": 100,
      "accuracy": 95,
      "pp": 10,
      "damage_class": "physical",
      "priority": 0
    },
    {
      "name": "Leer",
      "url": "https://pokeapi.co/api/v2/move/43/",
      "type": "Normal",
      "power": null,
      "accuracy": 100,
      "pp": 30,
      "damage_class": "status",
      "priority": 0
    },
    {
      "name": "Ice Beam",
      "url": "https://pokeapi.co/api/v2/move/58/",
      "type": "Ice",
      "power": 90,
      "accuracy": 100,
      "pp": 10,
      "damage_class": "special",
      "priority": 0
    },
    {
      "name": "Blizzard",
      "url": "https://pokeapi.co/api/v2/move/59/",
      "type": "Ice",
      "power": 110,
      "accuracy": 70,
      "pp": 5,
      "damage_class": "special",
      "priority": 0
    },
    {
      "name": "Hyper Beam",
      "url": "https://pokeapi.co/api/v2/move/63/",
      "type": "Normal",
      "power": 150,
      "accuracy": 90,
      "pp": 5,
      "damage_class": "special",
      "priority": 0
    },
    {
      "name": "Low Kick",
      "url": "https://pokeapi.co/api/v2/move/67/",
      "type": "Fighting",
      "power": null,
      "accuracy": 100,
      "pp": 20,
      "damage_class": "physical",
      "priority": 0
    },
    {
      "name": "Toxic",
      "url": "https://pokeapi.co/api/v2/move/92/",
      "type": "Poison",
      "power": null,
      "accuracy": 90,
      "pp": 10,
      "damage_class": "status",
      "priority": 0
    },
    {
      "name": "Agility",
      "url": "https://pokeapi.co/api/v2/move/97/",
      "type": "Psychic",
      "power": null,
      "accuracy": null,
      "pp": 30,
      "damage_class": "status",
      "priority": 0
    },
    {
      "name": "Double Team",
      "url": "https://pokeapi.co/api/v2/move/104/",
      "type": "Normal",
      "power": null,
      "accuracy": null,
      "pp": 15,
      "damage_class": "status",
      "priority": 0
    },
    {
      "name": "Swift",
      "url": "https://pokeapi.co/api/v2/move/129/",
      "type": "Normal",
      "power": 60,
      "accuracy": null,
      "pp": 20,
      "damage_class": "special",
      "priority": 0
    },
    {
      "name": "High Jump Kick",
      "url": "https://pokeapi.co/api/v2/move/136/",
      "type": "Fighting",
      "power": 130,
      "accuracy": 90,
      "pp": 10,
      "damage_class": "physical",
      "priority": 0
    },
    {
      "name": "Rest",
      "url": "https://pokeapi.co/api/v2/move/156/",
      "type": "Psychic",
      "power": null,
      "accuracy": null,
      "pp": 5,
      "damage_class": "status",
      "priority": 0
    },
    {
      "name": "Substitute",
      "url": "https://pokeapi.co/api/v2/move/164/",
      "type": "Normal",
      "power": null,
      "accuracy": null,
      "pp": 10,
      "damage_class": "status",
      "priority": 0
    }
  ],
  "habitat": "Unknown",
  "generation": 1,
  "rarity": "Common",
  "baseExperience": 257,
  "order": 972,
  "isDefault": true,
  "captureRate": 45,
  "baseHappiness": 0,
  "growthRate": "slow",
  "hatchCounter": 120,
  "hasGenderDifferences": false,
  "genderRate": -1,
  "forms": [
    {
      "name": "Pheromosa",
      "raw_name": "pheromosa",
      "form_name": "",
      "is_mega": false,
      "is_gigantamax": false,
      "is_battle_only": false,
      "is_default": true,
      "sprites": {
        "front_default": "https://raw.githubusercontent.com/PokeAPI/sprites/master/sprites/pokemon/795.png",
        "back_default": "https://raw.githubusercontent.com/PokeAPI/sprites/master/sprites/pokemon/back/795.png",
        "front_shiny": "https://raw.githubusercontent.com/PokeAPI/sprites/master/sprites/pokemon/shiny/795.png",
        "back_shiny": "https://raw.githubusercontent.com/PokeAPI/sprites/master/sprites/pokemon/back/shiny/795.png",
        "front_female": null,
        "back_female": null
      }
    }
  ],
  "varieties": [
    {
      "name": "Pheromosa",
      "raw_name": "pheromosa",
      "is_default": true,
      "url": "https://pokeapi.co/api/v2/pokemon/795/",
      "type": ""
    }
  ],
  "heldItems": [],
  "cries": {
    "latest": "https://raw.githubusercontent.com/PokeAPI/cries/main/cries/pokemon/latest/795.ogg",
    "legacy": null
  }
}