{
  "id": 800,
  "name": "Necrozma",
  "species": "Prism Pokémon",
  "type": [
    "Psychic"
  ],
  "typeDetails": [
    {
      "name": "Psychic",
      "slot": 1
    }
  ],
  "height": 2.4,
  "weight": 230,
  "abilities": [
    {
      "name": "Prism armor",
      "url": "https://pokeapi.co/api/v2/ability/232/",
      "is_hidden": false,
      "slot": 1
    }
  ],
  "baseStats": {
    "hp": 97,
    "attack": 107,
    "defense": 101,
    "specialAttack": 127,
    "specialDefense": 89,
    "speed": 79
  },
  "description": "Reminiscent of the Ultra Beasts, this life-form, apparently asleep underground, is thought to have come from another world in ancient times.",
  "flavorTexts": [
    {
      "text": "Reminiscent of the Ultra Beasts, this life-form, apparently asleep underground, is thought to have come from another world in ancient times.",
      "version": "sun"
    },
    {
      "text": "Light is apparently the source of its energy. It has an extraordinarily vicious disposition and is constantly firing off laser beams.",
      "version": "moon"
    },
    {
      "text": "It looks somehow pained as it rages around in search of light, which serves as its energy. It’s apparently from another world.",
      "version": "ultra-sun"
    },
    {
      "text": "Light is the source of its energy. If it isn’t devouring light, impurities build up in it and on it, and Necrozma darkens and stops moving.",
      "version": "ultra-moon"
    },
    {
      "text": "It survives by absorbing light. After a long time spent slumbering underground, impurities accumulated within it, causing its body to darken.",
      "version": "sword"
    }
  ],
  "colorPalette": {
    "primary": "#424a50",
    "secondary": "#2b3233",
    "accent": "#1b2021",
    "background": "#F8F8F8",
    "text": "#2C2C2C",
    "highlights": [
      "#424a50",
      "#2b3233",
      "#1b2021"
    ]
  },
  "artwork": {
    "official": "https://raw.githubusercontent.com/PokeAPI/sprites/master/sprites/pokemon/other/official-artwork/800.png",
    "front": "https://raw.githubusercontent.com/PokeAPI/sprites/master/sprites/pokemon/800.png",
    "back": "https://raw.githubusercontent.com/PokeAPI/sprites/master/sprites/pokemon/back/800.png",
    "shiny": "https://raw.githubusercontent.com/PokeAPI/sprites/master/sprites/pokemon/shiny/800.png",
    "back_shiny": "https://raw.githubusercontent.com/PokeAPI/sprites/master/sprites/pokemon/back/shiny/800.png",
    "front_female": null,
    "back_female": null,
    "front_shiny_female": null,
    "back_shiny_female": null
  },
  "evolution": [
    {
      "name": "Necrozma",
      "level": 1,
      "details": []
    }
  ],
  "moves": [
    {
      "name": "Swords Dance",
      "url": "https://pokeapi.co/api/v2/move/14/",
      "type": "Normal",
      "power": null,
      "accuracy": null,
      "pp": 20,
      "damage_class": "status",
      "priority": 0
    },
    {
      "name": "Body Slam",
      "url": "https://pokeapi.co/api/v2/move/34/",
      "type": "Normal",
      "power": 85,
      "accuracy": 100,
      "pp": 15,
      "damage_class": "physical",
      "priority": 0
    },
    {
      "name": "Hyper Beam",
      "url": "https://pokeapi.co/api/v2/move/63/",
      "type": "Normal",
      "power": 150,
      "accuracy": 90,
      "pp": 5,
      "damage_class": "special",
      "priority": 0
    },
    {
      "name": "Solar Beam",
      "url": "https://pokeapi.co/api/v2/move/76/",
      "type": "Grass",
      "power": 120,
      "accuracy": 100,
      "pp": 10,
      "damage_class": "special",
      "priority": 0
    },
    {
      "name": "Thunder Wave",
      "url": "https://pokeapi.co/api/v2/move/86/",
      "type": "Electric",
      "power": null,
      "accuracy": 90,
      "pp": 20,
      "damage_class": "status",
      "priority": 0
    },
    {
      "name": "Earthquake",
      "url": "https://pokeapi.co/api/v2/move/89/",
      "type": "Ground",
      "power": 100,
      "accuracy": 100,
      "pp": 10,
      "damage_class": "physical",
      "priority": 0
    },
    {
      "name": "Toxic",
      "url": "https://pokeapi.co/api/v2/move/92/",
      "type": "Poison",
      "power": null,
      "accuracy": 90,
      "pp": 10,
      "damage_class": "status",
      "priority": 0
    },
    {
      "name": "Confusion",
      "url": "https://pokeapi.co/api/v2/move/93/",
      "type": "Psychic",
      "power": 50,
      "accuracy": 100,
      "pp": 25,
      "damage_class": "special",
      "priority": 0
    },
    {
      "name": "Psychic",
      "url": "https://pokeapi.co/api/v2/move/94/",
      "type": "Psychic",
      "power": 90,
      "accuracy": 100,
      "pp": 10,
      "damage_class": "special",
      "priority": 0
    },
    {
      "name": "Double Team",
      "url": "https://pokeapi.co/api/v2/move/104/",
      "type": "Normal",
      "power": null,
      "accuracy": null,
      "pp": 15,
      "damage_class": "status",
      "priority": 0
    },
    {
      "name": "Light Screen",
      "url": "https://pokeapi.co/api/v2/move/113/",
      "type": "Psychic",
      "power": null,
      "accuracy": null,
      "pp": 30,
      "damage_class": "status",
      "priority": 0
    },
    {
      "name": "Reflect",
      "url": "https://pokeapi.co/api/v2/move/115/",
      "type": "Psychic",
      "power": null,
      "accuracy": null,
      "pp": 20,
      "damage_class": "status",
      "priority": 0
    },
    {
      "name": "Swift",
      "url": "https://pokeapi.co/api/v2/move/129/",
      "type": "Normal",
      "power": 60,
      "accuracy": null,
      "pp": 20,
      "damage_class": "special",
      "priority": 0
    },
    {
      "name": "Rest",
      "url": "https://pokeapi.co/api/v2/move/156/",
      "type": "Psychic",
      "power": null,
      "accuracy": null,
      "pp": 5,
      "damage_class": "status",
      "priority": 0
    },
    {
      "name": "Rock Slide",
      "url": "https://pokeapi.co/api/v2/move/157/",
      "type": "Rock",
      "power": 75,
      "accuracy": 90,
      "pp": 10,
      "damage_class": "physical",
      "priority": 0
    }
  ],
  "habitat": "Unknown",
  "generation": 1,
  "rarity": "Legendary",
  "baseExperience": 270,
  "order": 977,
  "isDefault": true,
  "captureRate": 255,
  "baseHappiness": 0,
  "growthRate": "slow",
  "hatchCounter": 120,
  "hasGenderDifferences": false,
  "genderRate": -1,
  "forms": [
    {
      "name": "Necrozma",
      "raw_name": "necrozma",
      "form_name": "",
      "is_mega": false,
      "is_gigantamax": false,
      "is_battle_only": false,
      "is_default": true,
      "sprites": {
        "front_default": "https://raw.githubusercontent.com/PokeAPI/sprites/master/sprites/pokemon/800.png",
        "back_default": "https://raw.githubusercontent.com/PokeAPI/sprites/master/sprites/pokemon/back/800.png",
        "front_shiny": "https://raw.githubusercontent.com/PokeAPI/sprites/master/sprites/pokemon/shiny/800.png",
        "back_shiny": "https://raw.githubusercontent.com/PokeAPI/sprites/master/sprites/pokemon/back/shiny/800.png",
        "front_female": null,
        "back_female": null
      }
    }
  ],
  "varieties": [
    {
      "name": "Necrozma",
      "raw_name": "necrozma",
      "is_default": true,
      "url": "https://pokeapi.co/api/v2/pokemon/800/",
      "type": ""
    },
    {
      "name": "Necrozma dusk",
      "raw_name": "necrozma-dusk",
      "is_default": false,
      "url": "https://pokeapi.co/api/v2/pokemon/10155/",
      "type": ""
    },
    {
      "name": "Necrozma dawn",
      "raw_name": "necrozma-dawn",
      "is_default": false,
      "url": "https://pokeapi.co/api/v2/pokemon/10156/",
      "type": ""
    },
    {
      "name": "Necrozma ultra",
      "raw_name": "necrozma-ultra",
      "is_default": false,
      "url": "https://pokeapi.co/api/v2/pokemon/10157/",
      "type": ""
    }
  ],
  "heldItems": [],
  "cries": {
    "latest": "https://raw.githubusercontent.com/PokeAPI/cries/main/cries/pokemon/latest/800.ogg",
    "legacy": null
  },
  "names": {
    "ja-Hrkt": "ネクロズマ",
    "roomaji": "Necrozma",
    "ko": "네크로즈마",
    "zh-Hant": "奈克洛茲瑪",
    "fr": "Necrozma",
    "de": "Necrozma",
    "es": "Necrozma",
    "it": "Necrozma",
    "en": "Necrozma",
    "ja": "ネクロズマ",
    "zh-Hans": "奈克洛兹玛"
  }
}