{
  "id": 94,
  "name": "Gengar",
  "species": "Shadow Pok\u00e9mon",
  "type": [
    "Ghost",
    "Poison"
  ],
  "typeDetails": [
    {
      "name": "Ghost",
      "slot": 1
    },
    {
      "name": "Poison",
      "slot": 2
    }
  ],
  "height": 1.5,
  "weight": 40.5,
  "abilities": [
    {
      "name": "Cursed body",
      "url": "https://pokeapi.co/api/v2/ability/130/",
      "is_hidden": false,
      "slot": 1
    }
  ],
  "baseStats": {
    "hp": 60,
    "attack": 65,
    "defense": 60,
    "specialAttack": 130,
    "specialDefense": 75,
    "speed": 110
  },
  "description": "Under a full moon, this POK\u00e9MON likes to mimic the shadows of people and laugh at their fright.",
  "flavorTexts": [
    {
      "text": "Under a full moon, this POK\u00e9MON likes to mimic the shadows of people and laugh at their fright.",
      "version": "red"
    },
    {
      "text": "Under a full moon, this POK\u00e9MON likes to mimic the shadows of people and laugh at their fright.",
      "version": "blue"
    },
    {
      "text": "A GENGAR is close by if you feel a sudden chill. It may be trying to lay a curse on you.",
      "version": "yellow"
    },
    {
      "text": "It steals heat from its surround\u00ad ings. If you feel a sudden chill, it is certain that a GENGAR appeared.",
      "version": "gold"
    },
    {
      "text": "To steal the life of its target, it slips into the prey's shadow and silently waits for an opportunity.",
      "version": "silver"
    }
  ],
  "colorPalette": {
    "primary": "#A8A878",
    "secondary": "#F8D030",
    "accent": "#F8F8F8",
    "background": "#F8F8F8",
    "text": "#2C2C2C",
    "highlights": [
      "#A8A878",
      "#F8D030",
      "#F8F8F8"
    ]
  },
  "artwork": {
    "official": "https://raw.githubusercontent.com/PokeAPI/sprites/master/sprites/pokemon/other/official-artwork/94.png",
    "front": "https://raw.githubusercontent.com/PokeAPI/sprites/master/sprites/pokemon/94.png",
    "back": "https://raw.githubusercontent.com/PokeAPI/sprites/master/sprites/pokemon/back/94.png",
    "shiny": "https://raw.githubusercontent.com/PokeAPI/sprites/master/sprites/pokemon/shiny/94.png",
    "back_shiny": "https://raw.githubusercontent.com/PokeAPI/sprites/master/sprites/pokemon/back/shiny/94.png",
    "front_female": null,
    "back_female": null,
    "front_shiny_female": null,
    "back_shiny_female": null
  },
  "evolution": [
    {
      "name": "Gastly",
      "level": 1,
      "details": []
    },
    {
      "name": "Haunter",
      "level": 2,
      "details": [
        {
          "min_level": 25,
          "trigger": "level up"
        }
      ]
    },
    {
      "name": "Gengar",
      "level": 3,
      "details": [
        {
          "trigger": "trade"
        }
      ]
    }
  ],
  "moves": [
    {
      "name": "Mega Punch",
      "url": "https://pokeapi.co/api/v2/move/5/",
      "type": "Normal",
      "power": 80,
      "accuracy": 85,
      "pp": 20,
      "damage_class": "physical",
      "priority": 0
    },
    {
      "name": "Fire Punch",
      "url": "https://pokeapi.co/api/v2/move/7/",
      "type": "Fire",
      "power": 75,
      "accuracy": 100,
      "pp": 15,
      "damage_class": "physical",
      "priority": 0
    },
    {
      "name": "Ice Punch",
      "url": "https://pokeapi.co/api/v2/move/8/",
      "type": "Ice",
      "power": 75,
      "accuracy": 100,
      "pp": 15,
      "damage_class": "physical",
      "priority": 0
    },
    {
      "name": "Thunder Punch",
      "url": "https://pokeapi.co/api/v2/move/9/",
      "type": "Electric",
      "power": 75,
      "accuracy": 100,
      "pp": 15,
      "damage_class": "physical",
      "priority": 0
    },
    {
      "name": "Mega Kick",
      "url": "https://pokeapi.co/api/v2/move/25/",
      "type": "Normal",
      "power": 120,
      "accuracy": 75,
      "pp": 5,
      "damage_class": "physical",
      "priority": 0
    },
    {
      "name": "Headbutt",
      "url": "https://pokeapi.co/api/v2/move/29/",
      "type": "Normal",
      "power": 70,
      "accuracy": 100,
      "pp": 15,
      "damage_class": "physical",
      "priority": 0
    },
    {
      "name": "Body Slam",
      "url": "https://pokeapi.co/api/v2/move/34/",
      "type": "Normal",
      "power": 85,
      "accuracy": 100,
      "pp": 15,
      "damage_class": "physical",
      "priority": 0
    },
    {
      "name": "Take Down",
      "url": "https://pokeapi.co/api/v2/move/36/",
      "type": "Normal",
      "power": 90,
      "accuracy": 85,
      "pp": 20,
      "damage_class": "physical",
      "priority": 0
    },
    {
      "name": "Double Edge",
      "url": "https://pokeapi.co/api/v2/move/38/",
      "type": "Normal",
      "power": 120,
      "accuracy": 100,
      "pp": 15,
      "damage_class": "physical",
      "priority": 0
    },
    {
      "name": "Disable",
      "url": "https://pokeapi.co/api/v2/move/50/",
      "type": "Normal",
      "power": null,
      "accuracy": 100,
      "pp": 20,
      "damage_class": "status",
      "priority": 0
    },
    {
      "name": "Hyper Beam",
      "url": "https://pokeapi.co/api/v2/move/63/",
      "type": "Normal",
      "power": 150,
      "accuracy": 90,
      "pp": 5,
      "damage_class": "special",
      "priority": 0
    },
    {
      "name": "Submission",
      "url": "https://pokeapi.co/api/v2/move/66/",
      "type": "Fighting",
      "power": 80,
      "accuracy": 80,
      "pp": 20,
      "damage_class": "physical",
      "priority": 0
    },
    {
      "name": "Counter",
      "url": "https://pokeapi.co/api/v2/move/68/",
      "type": "Fighting",
      "power": null,
      "accuracy": 100,
      "pp": 20,
      "damage_class": "physical",
      "priority": -5
    },
    {
      "name": "Seismic Toss",
      "url": "https://pokeapi.co/api/v2/move/69/",
      "type": "Fighting",
      "power": null,
      "accuracy": 100,
      "pp": 20,
      "damage_class": "physical",
      "priority": 0
    },
    {
      "name": "Strength",
      "url": "https://pokeapi.co/api/v2/move/70/",
      "type": "Normal",
      "power": 80,
      "accuracy": 100,
      "pp": 15,
      "damage_class": "physical",
      "priority": 0
    }
  ],
  "habitat": "Cave",
  "generation": 1,
  "rarity": "Common",
  "baseExperience": 225,
  "order": 149,
  "isDefault": true,
  "captureRate": 45,
  "baseHappiness": 70,
  "growthRate": "medium slow",
  "hatchCounter": 20,
  "hasGenderDifferences": false,
  "genderRate": 4,
  "forms": [
    {
      "name": "Gengar",
      "raw_name": "gengar",
      "form_name": "",
      "is_mega": false,
      "is_gigantamax": false,
      "is_battle_only": false,
      "is_default": true,
      "sprites": {
        "front_default": "https://raw.githubusercontent.com/PokeAPI/sprites/master/sprites/pokemon/94.png",
        "back_default": "https://raw.githubusercontent.com/PokeAPI/sprites/master/sprites/pokemon/back/94.png",
        "front_shiny": "https://raw.githubusercontent.com/PokeAPI/sprites/master/sprites/pokemon/shiny/94.png",
        "back_shiny": "https://raw.githubusercontent.com/PokeAPI/sprites/master/sprites/pokemon/back/shiny/94.png",
        "front_female": null,
        "back_female": null
      }
    }
  ],
  "varieties": [
    {
      "name": "Gengar",
      "raw_name": "gengar",
      "is_default": true,
      "url": "https://pokeapi.co/api/v2/pokemon/94/",
      "type": ""
    },
    {
      "name": "Gengar mega",
      "raw_name": "gengar-mega",
      "is_default": false,
      "url": "https://pokeapi.co/api/v2/pokemon/10038/",
      "type": "Mega"
    },
    {
      "name": "Gengar gmax",
      "raw_name": "gengar-gmax",
      "is_default": false,
      "url": "https://pokeapi.co/api/v2/pokemon/10202/",
      "type": "Gigantamax"
    }
  ],
  "heldItems": [
    {
      "name": "Spell Tag",
      "rarity": 5
    }
  ],
  "cries": {
    "latest": "https://raw.githubusercontent.com/PokeAPI/cries/main/cries/pokemon/latest/94.ogg",
    "legacy": "https://raw.githubusercontent.com/PokeAPI/cries/main/cries/pokemon/legacy/94.ogg"
  }
}